RsCMPX_NrFr1Meas/RsCMPX_NrFr1Meas.py
RsCMPX_NrFr1Meas/__init__.py
RsCMPX_NrFr1Meas/enums.py
RsCMPX_NrFr1Meas/repcap.py
RsCMPX_NrFr1Meas/CustomFiles/__init__.py
RsCMPX_NrFr1Meas/CustomFiles/events.py
RsCMPX_NrFr1Meas/CustomFiles/reliability.py
RsCMPX_NrFr1Meas/CustomFiles/utilities.py
RsCMPX_NrFr1Meas/Implementations/__init__.py
RsCMPX_NrFr1Meas/Implementations/Configure/__init__.py
RsCMPX_NrFr1Meas/Implementations/Configure/NrSubMeas/__init__.py
RsCMPX_NrFr1Meas/Implementations/Configure/NrSubMeas/BwConfig/Invoke.py
RsCMPX_NrFr1Meas/Implementations/Configure/NrSubMeas/BwConfig/__init__.py
RsCMPX_NrFr1Meas/Implementations/Configure/NrSubMeas/Caggregation/AcSpacing.py
RsCMPX_NrFr1Meas/Implementations/Configure/NrSubMeas/Caggregation/Cbandwidth.py
RsCMPX_NrFr1Meas/Implementations/Configure/NrSubMeas/Caggregation/__init__.py
RsCMPX_NrFr1Meas/Implementations/Configure/NrSubMeas/Caggregation/Frequency/Aggregated.py
RsCMPX_NrFr1Meas/Implementations/Configure/NrSubMeas/Caggregation/Frequency/__init__.py
RsCMPX_NrFr1Meas/Implementations/Configure/NrSubMeas/Cc/Cbandwidth.py
RsCMPX_NrFr1Meas/Implementations/Configure/NrSubMeas/Cc/Frequency.py
RsCMPX_NrFr1Meas/Implementations/Configure/NrSubMeas/Cc/Nallocations.py
RsCMPX_NrFr1Meas/Implementations/Configure/NrSubMeas/Cc/NbwParts.py
RsCMPX_NrFr1Meas/Implementations/Configure/NrSubMeas/Cc/PlcId.py
RsCMPX_NrFr1Meas/Implementations/Configure/NrSubMeas/Cc/Rpool.py
RsCMPX_NrFr1Meas/Implementations/Configure/NrSubMeas/Cc/TaPosition.py
RsCMPX_NrFr1Meas/Implementations/Configure/NrSubMeas/Cc/__init__.py
RsCMPX_NrFr1Meas/Implementations/Configure/NrSubMeas/Cc/Allocation/__init__.py
RsCMPX_NrFr1Meas/Implementations/Configure/NrSubMeas/Cc/Allocation/Pucch/IcShift.py
RsCMPX_NrFr1Meas/Implementations/Configure/NrSubMeas/Cc/Allocation/Pucch/IsfHopping.py
RsCMPX_NrFr1Meas/Implementations/Configure/NrSubMeas/Cc/Allocation/Pucch/Occ.py
RsCMPX_NrFr1Meas/Implementations/Configure/NrSubMeas/Cc/Allocation/Pucch/ShPrb.py
RsCMPX_NrFr1Meas-5.0.100.dist-info/METADATA
RsCMPX_NrFr1Meas-5.0.100.dist-info/WHEEL
RsCMPX_NrFr1Meas-5.0.100.dist-info/top_level.txt
RsCMPX_NrFr1Meas-5.0.100.dist-info/RECORD
